witpy/radon/__init__.py
witpy/radon/exceptions.py
witpy/radon/script.py
witpy/radon/types.py
witpy/transactions/__init__.py
witpy/transactions/data_request.py
witpy/transactions/exceptions.py
witpy/transactions/rad_request.py
witpy/util/__init__.py
witpy/util/cbor.py
witpy/util/string.py
witpy/util/system_handler.py
witpy/util/toml.py
witpy/util/utf.py
witpy/util/jsonrpc/__init__.py
witpy/util/jsonrpc/exceptions.py
witpy/util/jsonrpc/id_generators.py
witpy/util/jsonrpc/log.py
witpy/util/jsonrpc/parse.py
witpy/util/jsonrpc/requests.py
witpy/util/jsonrpc/response.py
witpy/util/websocket/__init__.py
witpy/util/websocket/abnf.py
witpy/util/websocket/app.py
witpy/util/websocket/core.py
witpy/util/websocket/exceptions.py
witpy/util/websocket/http.py
witpy/util/websocket/logging.py
witpy/util/websocket/socket.py
witpy/util/websocket/ssl_compat.py
witpy/wallet/__init__.py
witpy/wallet/client.py
witpy-0.9.0.dist-info/LICENSE
witpy-0.9.0.dist-info/METADATA
witpy-0.9.0.dist-info/WHEEL
witpy-0.9.0.dist-info/top_level.txt
witpy-0.9.0.dist-info/RECORD
