Metadata-Version: 2.1
Name: witpy
Version: 0.9.0
Summary: A JSON RPC client for the Witnet Protocol.
Home-page: https://github.com/parodyBit/witpy
Author-email: parody_bit@criptext.com
License: MIT License
Project-URL: Bug Reports, https://github.com/parodyBit/witpy/issues
Project-URL: Source, https://github.com/parodyBit/witpy/
Keywords: witnet wallet client json
Platform: UNKNOWN
Classifier: Development Status :: 3 - Alpha
Classifier: Intended Audience :: Developers
Classifier: Programming Language :: Python :: 3
Classifier: License :: OSI Approved :: MIT License
Requires-Python: >=3.4, <4
Requires-Dist: peppercorn
Requires-Dist: apply-defaults
Requires-Dist: attrs
Requires-Dist: cbor
Requires-Dist: click
Requires-Dist: importlib-metadata
Requires-Dist: pyrsistent
Requires-Dist: six
Requires-Dist: zipp
